omnilearned/__init__.py
omnilearned/_version.py
omnilearned/cli.py
omnilearned/dataloader.py
omnilearned/diffusion.py
omnilearned/layers.py
omnilearned/network.py
omnilearned/train.py
omnilearned/utils.py
omnilearned-0.1.0.dist-info/METADATA
omnilearned-0.1.0.dist-info/WHEEL
omnilearned-0.1.0.dist-info/entry_points.txt
omnilearned-0.1.0.dist-info/RECORD
