Metadata-Version: 2.4
Name: omnilearned
Version: 0.1.0
Summary: OmniLearned: A unified deep learning approach for particle physics
Project-URL: Homepage, https://github.com/ViniciusMikuni/OmniLearned
Project-URL: Bug Tracker, https://github.com/ViniciusMikuni/OmniLearned/issues
Author-email: Vinicius Mikuni <vmikuni@gmail.com>
License: MIT
Classifier: License :: OSI Approved :: MIT License
Classifier: Operating System :: OS Independent
Classifier: Programming Language :: Python :: 3
Classifier: Topic :: Scientific/Engineering :: Artificial Intelligence
Classifier: Topic :: Scientific/Engineering :: Physics
Requires-Python: >=3.8
Requires-Dist: einops>=0.8.1
Requires-Dist: h5py>=3.13.0
Requires-Dist: numpy>=2.2.4
Requires-Dist: pytorch-optimizer>=3.5.0
Requires-Dist: requests>=2.32.3
Requires-Dist: scikit-learn>=1.6.1
Requires-Dist: torch>=2.5.1
Requires-Dist: typer>=0.15.2
Provides-Extra: dev
Requires-Dist: black>=22.0.0; extra == 'dev'
Requires-Dist: flake8>=4.0.0; extra == 'dev'
Requires-Dist: hatch-vcs>=0.3.0; extra == 'dev'
Requires-Dist: isort>=5.10.0; extra == 'dev'
Requires-Dist: pytest>=7.0.0; extra == 'dev'
